compas_session/__init__.py
compas_session/history.py
compas_session/lazyload.py
compas_session/session.py
compas_session/settings.py
compas_session-0.7.0.dist-info/licenses/LICENSE
compas_session-0.7.0.dist-info/METADATA
compas_session-0.7.0.dist-info/WHEEL
compas_session-0.7.0.dist-info/top_level.txt
compas_session-0.7.0.dist-info/RECORD
